morax/__init__.py
morax/__main__.py
morax/config.yaml
morax/auth/__init__.py
morax/auth/auth.py
morax/auth/__pycache__/__init__.cpython-38.pyc
morax/auth/__pycache__/auth.cpython-38.pyc
morax/auth/static/error.svg
morax/auth/static/in-progress.svg
morax/auth/static/tick.png
morax/auth/templates/complete.html
morax/auth/templates/error.html
morax/auth/templates/in-progress.html
morax/auth/templates/running.html
morax/data/README.md
morax/data/__init__.py
morax/data/api.py
morax/data/chart.py
morax/data/view.py
morax/data/__pycache__/__init__.cpython-38.pyc
morax/data/__pycache__/api.cpython-38.pyc
morax/data/__pycache__/chart.cpython-38.pyc
morax/data/__pycache__/view.cpython-38.pyc
morax/data/assets/ascii.txt
morax/data/assets/btc.txt
morax/data/assets/doge.txt
morax/data/assets/eth.txt
morax/data/assets/ltc.txt
morax/data/assets/mana.txt
morax/data/assets/xlm.txt
morax/data/assets/xrp.txt
morax-1.0.7.dist-info/LICENSE
morax-1.0.7.dist-info/METADATA
morax-1.0.7.dist-info/WHEEL
morax-1.0.7.dist-info/entry_points.txt
morax-1.0.7.dist-info/top_level.txt
morax-1.0.7.dist-info/RECORD
