Metadata-Version: 2.1
Name: morax
Version: 1.0.7
Summary: A slick CLI tool to monitor coinbase crypto assets.
Home-page: https://github.com/punidramesh/Hades
Author: Punid Ramesh
Author-email: punidramesh@gmail.com
License: MIT
Keywords: wallet,console,coinbase,crypto,cli,terminal,term
Platform: UNKNOWN
Classifier: Programming Language :: Python
Classifier: Programming Language :: Python :: 3.5
Classifier: Programming Language :: Python :: 3.6
Classifier: Programming Language :: Python :: 3.7
Classifier: Programming Language :: Python :: 3.8
Classifier: Programming Language :: Python :: 3 :: Only
Requires-Python: >=3.4
License-File: LICENSE
Requires-Dist: aiohttp (==3.7.4.post0)
Requires-Dist: asciichartpy (==1.5.25)
Requires-Dist: async-timeout (==3.0.1)
Requires-Dist: attrs (==21.2.0)
Requires-Dist: certifi (==2020.12.5)
Requires-Dist: chardet (==4.0.0)
Requires-Dist: click (==8.0.0)
Requires-Dist: colorama (==0.4.4)
Requires-Dist: dateparser (==1.0.0)
Requires-Dist: Flask (==2.0.0)
Requires-Dist: halo (==0.0.31)
Requires-Dist: idna (==2.10)
Requires-Dist: itsdangerous (==2.0.0)
Requires-Dist: Jinja2 (==3.0.0)
Requires-Dist: log-symbols (==0.0.14)
Requires-Dist: MarkupSafe (==2.0.0)
Requires-Dist: multidict (==5.1.0)
Requires-Dist: python-dateutil (==2.8.1)
Requires-Dist: python-dotenv (==0.17.1)
Requires-Dist: pytz (==2021.1)
Requires-Dist: regex (==2021.4.4)
Requires-Dist: requests (==2.25.1)
Requires-Dist: six (==1.16.0)
Requires-Dist: spinners (==0.0.24)
Requires-Dist: termcolor (==1.1.0)
Requires-Dist: typing-extensions (==3.10.0.0)
Requires-Dist: tzlocal (==2.1)
Requires-Dist: ujson (==4.0.2)
Requires-Dist: urllib3 (==1.26.4)
Requires-Dist: websockets (==9.0.1)
Requires-Dist: Werkzeug (==2.0.0)
Requires-Dist: yarl (==1.6.3)
